{
  "$schema": "https://developer.microsoft.com/json-schemas/fabric/item/report/definition/visualContainer/2.4.0/schema.json",
  "name": "1655b2be07e4997c3b04",
  "position": {
    "x": 24,
    "y": 160,
    "z": 33000,
    "height": 34,
    "width": 400,
    "tabOrder": 30000
  },
  "visual": {
    "visualType": "basicShape",
    "objects": {
      "general": [
        {
          "properties": {
            "shapeType": {
              "expr": {
                "Literal": {
                  "Value": "'line'"
                }
              }
            }
          }
        }
      ],
      "line": [
        {
          "properties": {
            "weight": {
              "expr": {
                "Literal": {
                  "Value": "0.5D"
                }
              }
            }
          }
        }
      ],
      "rotation": [
        {
          "properties": {
            "angle": {
              "expr": {
                "Literal": {
                  "Value": "90D"
                }
              }
            }
          }
        }
      ]
    },
    "drillFilterOtherVisuals": true
  }
}