{
  "$schema": "https://developer.microsoft.com/json-schemas/fabric/item/report/definition/visualContainer/2.4.0/schema.json",
  "name": "c0660fe068af78a81a1b",
  "position": {
    "x": 150.52087845346463,
    "y": 5.7815119800739012,
    "z": 2000,
    "height": 24.615384615384617,
    "width": 126.5934065934066,
    "tabOrder": 33000
  },
  "visual": {
    "visualType": "textbox",
    "objects": {
      "general": [
        {
          "properties": {
            "paragraphs": [
              {
                "textRuns": [
                  {
                    "value": "C A N T I D A D   I T E M S"
                  }
                ],
                "horizontalTextAlignment": "right"
              }
            ]
          }
        }
      ]
    },
    "visualContainerObjects": {
      "background": [
        {
          "properties": {
            "show": {
              "expr": {
                "Literal": {
                  "Value": "false"
                }
              }
            }
          }
        }
      ]
    },
    "drillFilterOtherVisuals": true
  },
  "parentGroupName": "0a53977190e6252d5696"
}